llmtuner/__init__.py
llmtuner/cli.py
llmtuner/api/__init__.py
llmtuner/api/app.py
llmtuner/api/chat.py
llmtuner/api/common.py
llmtuner/api/protocol.py
llmtuner/chat/__init__.py
llmtuner/chat/base_engine.py
llmtuner/chat/chat_model.py
llmtuner/chat/hf_engine.py
llmtuner/chat/vllm_engine.py
llmtuner/data/__init__.py
llmtuner/data/aligner.py
llmtuner/data/collator.py
llmtuner/data/formatter.py
llmtuner/data/loader.py
llmtuner/data/parser.py
llmtuner/data/preprocess.py
llmtuner/data/template.py
llmtuner/data/utils.py
llmtuner/eval/__init__.py
llmtuner/eval/evaluator.py
llmtuner/eval/template.py
llmtuner/extras/__init__.py
llmtuner/extras/callbacks.py
llmtuner/extras/constants.py
llmtuner/extras/logging.py
llmtuner/extras/misc.py
llmtuner/extras/packages.py
llmtuner/extras/ploting.py
llmtuner/hparams/__init__.py
llmtuner/hparams/data_args.py
llmtuner/hparams/evaluation_args.py
llmtuner/hparams/finetuning_args.py
llmtuner/hparams/generating_args.py
llmtuner/hparams/model_args.py
llmtuner/hparams/parser.py
llmtuner/model/__init__.py
llmtuner/model/adapter.py
llmtuner/model/loader.py
llmtuner/model/patcher.py
llmtuner/model/utils/__init__.py
llmtuner/model/utils/attention.py
llmtuner/model/utils/checkpointing.py
llmtuner/model/utils/embedding.py
llmtuner/model/utils/longlora.py
llmtuner/model/utils/misc.py
llmtuner/model/utils/mod.py
llmtuner/model/utils/moe.py
llmtuner/model/utils/quantization.py
llmtuner/model/utils/rope.py
llmtuner/model/utils/unsloth.py
llmtuner/model/utils/valuehead.py
llmtuner/model/utils/visual.py
llmtuner/train/__init__.py
llmtuner/train/tuner.py
llmtuner/train/utils.py
llmtuner/train/dpo/__init__.py
llmtuner/train/dpo/trainer.py
llmtuner/train/dpo/workflow.py
llmtuner/train/orpo/__init__.py
llmtuner/train/orpo/trainer.py
llmtuner/train/orpo/workflow.py
llmtuner/train/ppo/__init__.py
llmtuner/train/ppo/trainer.py
llmtuner/train/ppo/utils.py
llmtuner/train/ppo/workflow.py
llmtuner/train/pt/__init__.py
llmtuner/train/pt/trainer.py
llmtuner-0.7.1.dist-info/LICENSE
llmtuner-0.7.1.dist-info/METADATA
llmtuner-0.7.1.dist-info/WHEEL
llmtuner-0.7.1.dist-info/entry_points.txt
llmtuner-0.7.1.dist-info/top_level.txt
llmtuner-0.7.1.dist-info/RECORD
