Metadata-Version: 2.1
Name: llmtuner
Version: 0.7.1
Summary: Easy-to-use LLM fine-tuning framework
Home-page: https://github.com/hiyouga/LLaMA-Factory
Author: hiyouga
Author-email: hiyouga@buaa.edu.cn
License: Apache 2.0 License
Keywords: LLaMA,BLOOM,Falcon,LLM,ChatGPT,transformer,pytorch,deep learning
Classifier: Development Status :: 4 - Beta
Classifier: Intended Audience :: Developers
Classifier: Intended Audience :: Education
Classifier: Intended Audience :: Science/Research
Classifier: License :: OSI Approved :: Apache Software License
Classifier: Operating System :: OS Independent
Classifier: Programming Language :: Python :: 3
Classifier: Programming Language :: Python :: 3.8
Classifier: Programming Language :: Python :: 3.9
Classifier: Programming Language :: Python :: 3.10
Classifier: Programming Language :: Python :: 3.11
Classifier: Topic :: Scientific/Engineering :: Artificial Intelligence
Requires-Python: >=3.8.0
License-File: LICENSE
Requires-Dist: transformers >=4.37.2
Requires-Dist: datasets >=2.14.3
Requires-Dist: accelerate >=0.27.2
Requires-Dist: peft >=0.10.0
Requires-Dist: trl >=0.8.1
Requires-Dist: gradio >=4.0.0
Requires-Dist: scipy
Requires-Dist: einops
Requires-Dist: sentencepiece
Requires-Dist: protobuf
Requires-Dist: uvicorn
Requires-Dist: pydantic
Requires-Dist: fastapi
Requires-Dist: sse-starlette
Requires-Dist: matplotlib >=3.7.0
Requires-Dist: fire
Requires-Dist: packaging
Requires-Dist: pyyaml
Provides-Extra: aqlm
Requires-Dist: aqlm[gpu] >=1.1.0 ; extra == 'aqlm'
Provides-Extra: awq
Requires-Dist: autoawq ; extra == 'awq'
Provides-Extra: badam
Requires-Dist: badam ; extra == 'badam'
Provides-Extra: bitsandbytes
Requires-Dist: bitsandbytes >=0.39.0 ; extra == 'bitsandbytes'
Provides-Extra: deepspeed
Requires-Dist: deepspeed <=0.14.0,>=0.10.0 ; extra == 'deepspeed'
Provides-Extra: galore
Requires-Dist: galore-torch ; extra == 'galore'
Provides-Extra: gptq
Requires-Dist: optimum >=1.16.0 ; extra == 'gptq'
Requires-Dist: auto-gptq >=0.5.0 ; extra == 'gptq'
Provides-Extra: metrics
Requires-Dist: nltk ; extra == 'metrics'
Requires-Dist: jieba ; extra == 'metrics'
Requires-Dist: rouge-chinese ; extra == 'metrics'
Provides-Extra: modelscope
Requires-Dist: modelscope ; extra == 'modelscope'
Provides-Extra: quality
Requires-Dist: ruff ; extra == 'quality'
Provides-Extra: qwen
Requires-Dist: tiktoken ; extra == 'qwen'
Requires-Dist: transformers-stream-generator ; extra == 'qwen'
Provides-Extra: torch
Requires-Dist: torch >=1.13.1 ; extra == 'torch'
Provides-Extra: vllm
Requires-Dist: vllm >=0.4.0 ; extra == 'vllm'
